erisforge/__init__.py
erisforge/eris_forge.py
erisforge/assets/llm_models.json
erisforge/layers/__init__.py
erisforge/layers/layers.py
erisforge/scorers/__init__.py
erisforge/scorers/base_scorer.py
erisforge/scorers/refusal_scorer/__init__.py
erisforge/scorers/refusal_scorer/expression_refusal_scorer.py
erisforge/scorers/refusal_scorer/llama_guard_refusal_scorer.py
erisforge/utils/__init__.py
erisforge/utils/layer_utils.py
ErisForge-1.1.0.dist-info/METADATA
ErisForge-1.1.0.dist-info/WHEEL
ErisForge-1.1.0.dist-info/top_level.txt
ErisForge-1.1.0.dist-info/RECORD
