Metadata-Version: 2.2
Name: ErisForge
Version: 1.1.0
Summary: Library for layer ablation/addition of LLM models
Author-email: Matteo Villosio <github@matteovillosio.com>
Project-URL: Homepage, https://github.com/Tsadoq/ErisForge
Project-URL: Bug Tracker, https://github.com/tsadoq/ErisForge/issues
Classifier: Programming Language :: Python :: 3
Classifier: License :: OSI Approved :: MIT License
Requires-Python: >=3.11
Requires-Dist: torch~=2.5.1
Requires-Dist: torchvision~=0.20.1
Requires-Dist: torchaudio~=2.5.1
Requires-Dist: tqdm~=4.67.0
Requires-Dist: transformers~=4.46.2
Requires-Dist: einops~=0.8.0
Requires-Dist: tiktoken~=0.8.0
